tribler_debug_ui/__init__.py
tribler_debug_ui/endpoint.py
tribler_debug_ui/app/dist/3rdpartylicenses.txt
tribler_debug_ui/app/dist/favicon.ico
tribler_debug_ui/app/dist/index.html
tribler_debug_ui/app/dist/main-es2015.638a7c4d7e424e39d5f2.js
tribler_debug_ui/app/dist/main-es5.638a7c4d7e424e39d5f2.js
tribler_debug_ui/app/dist/polyfills-es2015.f332a089ad1600448873.js
tribler_debug_ui/app/dist/polyfills-es5.177e85a9724683782539.js
tribler_debug_ui/app/dist/runtime-es2015.0dae8cbc97194c7caed4.js
tribler_debug_ui/app/dist/runtime-es5.0dae8cbc97194c7caed4.js
tribler_debug_ui/app/dist/styles.66f0b02054a12b03b2ca.css
tribler_debug_ui/app/dist/assets/js/sha1.min.js
tribler_debug_ui-0.0.3.dist-info/LICENSE
tribler_debug_ui-0.0.3.dist-info/METADATA
tribler_debug_ui-0.0.3.dist-info/WHEEL
tribler_debug_ui-0.0.3.dist-info/top_level.txt
tribler_debug_ui-0.0.3.dist-info/RECORD
